{"name":"mio","counts":{"deprecated":0,"unstable":14,"stable":132,"unmarked":352},"submodules":[{"name":"buf","counts":{"deprecated":0,"unstable":0,"stable":7,"unmarked":54},"submodules":[]},{"name":"prelude","counts":{"deprecated":0,"unstable":0,"stable":0,"unmarked":1},"submodules":[]},{"name":"tcp","counts":{"deprecated":0,"unstable":6,"stable":22,"unmarked":36},"submodules":[]},{"name":"udp","counts":{"deprecated":0,"unstable":8,"stable":7,"unmarked":12},"submodules":[]},{"name":"unix","counts":{"deprecated":0,"unstable":0,"stable":22,"unmarked":52},"submodules":[]},{"name":"util","counts":{"deprecated":0,"unstable":0,"stable":5,"unmarked":21},"submodules":[]}]}